lidaco
