Metadata-Version: 2.1
Name: lidaco
Version: 0.0.25
Summary: Wind Lidar Data Converter.
Home-page: https://github.com/e-WindLidar/Lidaco
Author: e-WindLidar
Author-email: e-windlidar@googlegroups.com
License: UNKNOWN
Keywords: wind,lidar,data,converter
Platform: UNKNOWN
